specable/__init__.py
specable/dicts.py
specable/inout.py
specable/interface.py
specable/specable.py
specable-0.1.1.dist-info/METADATA
specable-0.1.1.dist-info/WHEEL
specable-0.1.1.dist-info/RECORD
