Metadata-Version: 2.1
Name: specable
Version: 0.1.1
Summary: dictionaries to objects and vice versa
License: MIT
Author: Marcel Langer
Author-email: dev@marcel.science
Requires-Python: >=3.7,<4.0
Classifier: License :: OSI Approved :: MIT License
Classifier: Programming Language :: Python :: 3
Classifier: Programming Language :: Python :: 3.7
Classifier: Programming Language :: Python :: 3.8
Classifier: Programming Language :: Python :: 3.9
Classifier: Programming Language :: Python :: 3.10
Classifier: Programming Language :: Python :: 3.11
Requires-Dist: PyYAML
